{
    "content_logo": "",
    "content_title": "401",
    "content_sub_title": "Ooops we got you, access restricted.",
    "content_description": "If you want, you can always try and ask us to give you an access key to this informantion.",
    "design_background_image": "/static/images/backgrounds/003.jpeg",
    "design_background_color": "",
    "design_background_repeat": "",
    "design_font_family": "",
    "design_font_color": "",
    "design_content_alignment": "",
    "design_content_direction": "",
    "design_additional_styles": "",
    "search_results_title": "401 Unauthorized",
    "search_results_description": ""
}
